{
    "email": "<<okta_webhook.body.data.events[0].target[0].alternateId>>",
    "display_name": "<<okta_webhook.body.data.events[0].target[0].displayName>>",
    "event": "<<okta_webhook.body.data.events[0].eventType>>",
    "timestamp": "<<okta_webhook.body.data.events[0].published>>",
    "event_message": "<<okta_webhook.body.data.events[0].displayMessage>>",
    "group": "<<okta_webhook.body.data.events[0].target[1].displayName>>",
    "eventId": "<<okta_webhook.body.data.events[0].uuid>>",
    "team": "<<get_okta_user.body.profile.team>>",
    "department": "<<get_okta_user.body.profile.department>>",
    "title": "<<get_okta_user.body.profile.title>>",
    "profile_change": "<<okta_webhook.body.data.events[0].debugContext.debugData.changedAttributes>>"
  }